pl_compare/__init__.py
pl_compare/compare.py
pl_compare/examples.py
pl_compare/report.py
pl_compare/tests/__init__.py
pl_compare/tests/test_compare.py
pl_compare-0.9.3.dist-info/licenses/LICENSE
pl_compare-0.9.3.dist-info/METADATA
pl_compare-0.9.3.dist-info/WHEEL
pl_compare-0.9.3.dist-info/top_level.txt
pl_compare-0.9.3.dist-info/RECORD
