Metadata-Version: 2.4
Name: pl_compare
Version: 0.9.3
Summary: A tool to find the differences between two tables.
Author-email: Your Name <you@example.com>
Project-URL: Repository, https://github.com/concur1/pl_compare
Project-URL: Changelog, https://github.com/concur1/pl_compare/releases
Requires-Python: >3.9
License-File: LICENSE
Requires-Dist: polars>=1.24.0
Dynamic: license-file
